{"Euro": "0.928010", "British Pound": "0.793734", "Indian Rupee": "83.013831", "Australian Dollar": "1.531161", "Canadian Dollar": "1.348751", "Singapore Dollar": "1.346821", "Swiss Franc": "0.880617", "Malaysian Ringgit": "4.779707", "Japanese Yen": "150.226348", "Chinese Yuan Renminbi": "7.192796", "Argentine Peso": "835.001646", "Bahraini Dinar": "0.376000", "Botswana Pula": "13.713340", "Brazilian Real": "4.967916", "Bruneian Dollar": "1.346821", "Bulgarian Lev": "1.815030", "Chilean Peso": "969.831519", "Colombian Peso": "3908.447501", "Czech Koruna": "23.600055", "Danish Krone": "6.919194", "Hong Kong Dollar": "7.822322", "Hungarian Forint": "360.811698", "Icelandic Krona": "138.143458", "Indonesian Rupiah": "15618.257695", "Iranian Rial": "42002.597087", "Israeli Shekel": "3.607100", "Kazakhstani Tenge": "449.411633", "South Korean Won": "1331.564945", "Kuwaiti Dinar": "0.309002", "Libyan Dinar": "4.847372", "Mauritian Rupee": "46.899959", "Mexican Peso": "17.062102", "Nepalese Rupee": "132.884390", "New Zealand Dollar": "1.632650", "Norwegian Krone": "10.496657", "Omani Rial": "0.385102", "Pakistani Rupee": "279.339812", "Philippine Peso": "55.959851", "Polish Zloty": "4.030054", "Qatari Riyal": "3.640000", "Romanian New Leu": "4.618552", "Russian Ruble": "92.050241", "Saudi Arabian Riyal": "3.750000", "South African Rand": "18.861734", "Sri Lankan Rupee": "312.599728", "Swedish Krona": "10.443065", "Taiwan New Dollar": "31.390097", "Thai Baht": "36.011482", "Trinidadian Dollar": "6.777357", "Turkish Lira": "30.835301", "Emirati Dirham": "3.672500", "Venezuelan Bolivar": "3618866.173928"}